src/CnkiPythonMeta.py
cnkipythonmeta-0.1.7.dist-info/METADATA
cnkipythonmeta-0.1.7.dist-info/WHEEL
cnkipythonmeta-0.1.7.dist-info/licenses/LICENSE
cnkipythonmeta-0.1.7.dist-info/RECORD
