Metadata-Version: 2.1
Name: CnkiPythonMeta
Version: 0.1.7
Summary: A computational method and program CnkiPythonMeta based on the Python programming language for summarzing the data from CNKI.
Project-URL: Homepage, https://github.com/CnkiPythonMeta/CnkiPythonMeta
Project-URL: Bug Tracker, https://github.com/CnkiPythonMeta/CnkiPythonMeta/issues
Author-email: Guixian Yang <Ygxyoung@hotmail.com>
License-File: LICENSE
Classifier: License :: OSI Approved :: MIT License
Classifier: Programming Language :: Python :: 3
Requires-Python: >=3.7
